edfrw/__init__.py
edfrw/headers.py
edfrw/reader.py
edfrw/writer.py
edfrw-1.0.0.dist-info/LICENSE
edfrw-1.0.0.dist-info/METADATA
edfrw-1.0.0.dist-info/WHEEL
edfrw-1.0.0.dist-info/top_level.txt
edfrw-1.0.0.dist-info/RECORD
