Metadata-Version: 2.1
Name: edfrw
Version: 1.0.0
Summary: Read and write European Data Format (EDF) files
Home-page: https://github.com/antgon/edfrw
Author: Antonio González
Author-email: antgon@cantab.net
Project-URL: Bug Tracker, https://github.com/antgon/edfrw/issues
Classifier: Intended Audience :: Science/Research
Classifier: License :: OSI Approved :: GNU General Public License v3 or later (GPLv3+)
Classifier: Operating System :: OS Independent
Classifier: Programming Language :: Python :: 3
Classifier: Topic :: Scientific/Engineering
Classifier: Topic :: Scientific/Engineering :: Medical Science Apps.
Requires-Python: >=3.5
License-File: LICENSE
